isagog_userauth/__init__.py
isagog_userauth/base.py
isagog_userauth/config.py
isagog_userauth/custom_exceptions.py
isagog_userauth/database.py
isagog_userauth/db_session.py
isagog_userauth/main.py
isagog_userauth/models.py
isagog_userauth/routers/user.py
isagog_userauth/schemas.py
isagog_userauth/utils/gencrypt.py
isagog_userauth/utils.py
isagog_userauth-0.1.0.dist-info/LICENSE.md
isagog_userauth-0.1.0.dist-info/METADATA
isagog_userauth-0.1.0.dist-info/WHEEL
isagog_userauth-0.1.0.dist-info/RECORD
