Metadata-Version: 2.1
Name: isagog-userauth
Version: 0.1.0
Summary: A FastAPI project to manage users and issue JWT tokens to control access
Author: Robert Alexander
Author-email: gogonegro@gmail.com
Requires-Python: >=3.11,<4.0
Classifier: Programming Language :: Python :: 3
Classifier: Programming Language :: Python :: 3.11
Classifier: Programming Language :: Python :: 3.12
Requires-Dist: bcrypt (>=4.1.3,<5.0.0)
Requires-Dist: fastapi (>=0.111.0,<0.112.0)
Requires-Dist: passlib (>=1.7.4,<2.0.0)
Requires-Dist: pyjwt (>=2.8.0,<3.0.0)
Requires-Dist: python-dotenv (>=1.0.1,<2.0.0)
Requires-Dist: sqlalchemy (>=2.0.30,<3.0.0)
Requires-Dist: uvicorn (>=0.30.1,<0.31.0)
